newsdata_client/__init__.py
newsdata_client/newsdata_auth.py
newsdata_client/newsdata_client.py
newsdata_client/newsdata_client_helper.py
newsdata_client/newsdata_exception.py
newsdata_client/utils.py
newsdata_client-0.1.0.dist-info/licenses/LICENSE
newsdata_client-0.1.0.dist-info/WHEEL
newsdata_client-0.1.0.dist-info/METADATA
newsdata_client-0.1.0.dist-info/RECORD
