Metadata-Version: 2.4
Name: newsdata-client
Version: 0.1.0
Summary: Newsdata Python Client
Keywords: newsdata,news,newsdata-api
Author: Aditya Vikram Singh
Author-email: Aditya Vikram Singh <adivik672@gmail.com>
License-Expression: MIT
License-File: LICENSE
Classifier: Programming Language :: Python :: 3
Classifier: License :: OSI Approved :: MIT License
Requires-Dist: python-dotenv>=1.1.1
Requires-Dist: requests>=2.32.5
Requires-Python: >=3.13
Project-URL: Homepage, https://github.com/Vikuuu/newsdata-client
Project-URL: Issues, https://github.com/Vikuuu/newsdata-client/issues
